simqdsvr/__init__.py
simqdsvr/debug.py
simqdsvr/service_providers.py
simqdsvr/simqd.py
simqd-0.1.0.dist-info/LICENSE
simqd-0.1.0.dist-info/METADATA
simqd-0.1.0.dist-info/WHEEL
simqd-0.1.0.dist-info/entry_points.txt
simqd-0.1.0.dist-info/top_level.txt
simqd-0.1.0.dist-info/RECORD
