Metadata-Version: 2.1
Name: simqd
Version: 0.1.0
Summary: SIMQ服务提供者，同时也是SIMQ消息的消费者。
Author: Chen Han
Maintainer: Chen Han
License: Apache License, Version 2.0
Keywords: simq,simqd
Classifier: Development Status :: 5 - Production/Stable
Classifier: Intended Audience :: Developers
Classifier: Topic :: Software Development :: Libraries :: Python Modules
Classifier: License :: OSI Approved :: Apache Software License
Classifier: Programming Language :: Python :: 3
Classifier: Programming Language :: Python :: 3 :: Only
License-File: LICENSE
Requires-Dist: graceful-sigterm
Requires-Dist: click
Requires-Dist: zenutils
Requires-Dist: simqclient
